fstree/_DirNode.py
fstree/_FileNode.py
fstree/_FsTree.py
fstree/_Node.py
fstree/__init__.py
fstree/_shared.py
fstree/utils.py
fstree-1.0.7.dist-info/METADATA
fstree-1.0.7.dist-info/WHEEL
fstree-1.0.7.dist-info/top_level.txt
fstree-1.0.7.dist-info/RECORD
