Metadata-Version: 2.1
Name: fstree
Version: 1.0.7
Summary: A tree structure to store files & directories.
Home-page: https://github.com/hweickert/fstree
Author: Henry Weickert
Author-email: henryweickert@gmail.com
License: UNKNOWN
Platform: UNKNOWN
Requires-Dist: six
Requires-Dist: anytree (==2.4.3)
Requires-Dist: oyaml (==0.9)
